mandelbrot_synthesizer/__init__.py
mandelbrot_synthesizer/config.py
mandelbrot_synthesizer/Library/__init__.py
mandelbrot_synthesizer/MandelbrotSynthesizer.py
mandelbrot_synthesizer/MandelbrotWindow.py
mandelbrot_synthesizer/MelodyMakerWindow.py
mandelbrot_synthesizer/Naming.py
mandelbrot_synthesizer/requirements.txt
mandelbrot_synthesizer/Styling.tcss
mandelbrot_synthesizer/UI.py
mandelbrot_synthesizer-0.1.12.dist-info/entry_points.txt
mandelbrot_synthesizer-0.1.12.dist-info/METADATA
mandelbrot_synthesizer-0.1.12.dist-info/WHEEL
mandelbrot_synthesizer-0.1.12.dist-info/RECORD
