Metadata-Version: 2.3
Name: mandelbrot_synthesizer
Version: 0.1.12
Summary: This tool converts the escape time of each point in various fractals to a tone that can be used to make simple melodies
License: MIT
Author: Yahia
Requires-Python: >=3.8
Classifier: License :: OSI Approved :: MIT License
Classifier: Programming Language :: Python :: 3
Classifier: Programming Language :: Python :: 3.8
Classifier: Programming Language :: Python :: 3.9
Classifier: Programming Language :: Python :: 3.10
Classifier: Programming Language :: Python :: 3.11
Classifier: Programming Language :: Python :: 3.12
Classifier: Programming Language :: Python :: 3.13
Requires-Dist: pygame (>=2.5.0)
Requires-Dist: textual (>=0.44.0)
Requires-Dist: textual-canvas (>=0.4.0)
